[[0.782421,{"lines":{"0":[["                                                                                                                                                                                                                                              ",{}]],"1":[["                                                                                                                                                                                                                                              ",{}]],"2":[["                                                                                                                                                                                                                                              ",{}]],"3":[["                                                                                                                                                                                                                                              ",{}]],"4":[["                                                                                                                                                                                                                                              ",{}]],"5":[["                                                                                                                                                                                                                                              ",{}]],"6":[["                                                                                                                                                                                                                                              ",{}]],"7":[["                                                                                                                                                                                                                                              ",{}]],"8":[["                                                                                                                                                                                                                                              ",{}]],"9":[["                                                                                                                                                                                                                                              ",{}]],"10":[["                                                                                                                                                                                                                                              ",{}]],"11":[["                                                                                                                                                                                                                                              ",{}]],"12":[["                                                                                                                                                                                                                                              ",{}]],"13":[["                                                                                                                                                                                                                                              ",{}]],"14":[["                                                                                                                                                                                                                                              ",{}]],"15":[["                                                                                                                                                                                                                                              ",{}]],"16":[["                                                                                                                                                                                                                                              ",{}]],"17":[["                                                                                                                                                                                                                                              ",{}]],"18":[["                                                                                                                                                                                                                                              ",{}]],"19":[["                                                                                                                                                                                                                                              ",{}]],"20":[["                                                                                                                                                                                                                                              ",{}]],"21":[["                                                                                                                                                                                                                                              ",{}]],"22":[["                                                                                                                                                                                                                                              ",{}]],"23":[["                                                                                                                                                                                                                                              ",{}]],"24":[["                                                                                                                                                                                                                                              ",{}]],"25":[["                                                                                                                                                                                                                                              ",{}]],"26":[["                                                                                                                                                                                                                                              ",{}]],"27":[["                                                                                                                                                                                                                                              ",{}]],"28":[["                                                                                                                                                                                                                                              ",{}]],"29":[["                                                                                                                                                                                                                                              ",{}]],"30":[["                                                                                                                                                                                                                                              ",{}]],"31":[["                                                                                                                                                                                                                                              ",{}]],"32":[["                                                                                                                                                                                                                                              ",{}]],"33":[["                                                                                                                                                                                                                                              ",{}]],"34":[["                                                                                                                                                                                                                                              ",{}]],"35":[["                                                                                                                                                                                                                                              ",{}]],"36":[["                                                                                                                                                                                                                                              ",{}]],"37":[["                                                                                                                                                                                                                                              ",{}]],"38":[["                                                                                                                                                                                                                                              ",{}]],"39":[["                                                                                                                                                                                                                                              ",{}]],"40":[["                                                                                                                                                                                                                                              ",{}]],"41":[["                                                                                                                                                                                                                                              ",{}]],"42":[["                                                                                                                                                                                                                                              ",{}]],"43":[["                                                                                                                                                                                                                                              ",{}]],"44":[["                                                                                                                                                                                                                                              ",{}]],"45":[["                                                                                                                                                                                                                                              ",{}]],"46":[["                                                                                                                                                                                                                                              ",{}]],"47":[["                                                                                                                                                                                                                                              ",{}]],"48":[["                                                                                                                                                                                                                                              ",{}]],"49":[["                                                                                                                                                                                                                                              ",{}]],"50":[["                                                                                                                                                                                                                                              ",{}]],"51":[["                                                                                                                                                                                                                                              ",{}]],"52":[["                                                                                                                                                                                                                                              ",{}]],"53":[["                                                                                                                                                                                                                                              ",{}]]},"cursor":{"x":0,"y":0,"visible":true}}],[0.156547,{"lines":{"0":[[" INSERT ",{"fg":22,"bg":148,"bold":true}],[" ",{"fg":148,"bg":31}],["wilmoore ",{"fg":231,"bg":31,"bold":true}],[" ",{"fg":31,"bg":240}],["/ ",{"fg":250,"bg":240}],[" ",{"fg":245,"bg":240}],["tmp ",{"fg":252,"bg":240,"bold":true}],[" ",{"fg":240}],["                                                                                                                                                                                                               ",{}]]},"cursor":{"x":31}}],[0.000244,{}],[0.154721,{}],[1.058022,{"lines":{"0":[[" INSERT ",{"fg":22,"bg":148,"bold":true}],[" ",{"fg":148,"bg":31}],["wilmoore ",{"fg":231,"bg":31,"bold":true}],[" ",{"fg":31,"bg":240}],["/ ",{"fg":250,"bg":240}],[" ",{"fg":245,"bg":240}],["tmp ",{"fg":252,"bg":240,"bold":true}],[" ",{"fg":240}],["b                                                                                                                                                                                                              ",{}]]},"cursor":{"x":32}}],[0.255251,{"lines":{"0":[[" INSERT ",{"fg":22,"bg":148,"bold":true}],[" ",{"fg":148,"bg":31}],["wilmoore ",{"fg":231,"bg":31,"bold":true}],[" ",{"fg":31,"bg":240}],["/ ",{"fg":250,"bg":240}],[" ",{"fg":245,"bg":240}],["tmp ",{"fg":252,"bg":240,"bold":true}],[" ",{"fg":240}],["br                                                                                                                                                                                                             ",{}]]},"cursor":{"x":33}}],[0.087871,{"lines":{"0":[[" INSERT ",{"fg":22,"bg":148,"bold":true}],[" ",{"fg":148,"bg":31}],["wilmoore ",{"fg":231,"bg":31,"bold":true}],[" ",{"fg":31,"bg":240}],["/ ",{"fg":250,"bg":240}],[" ",{"fg":245,"bg":240}],["tmp ",{"fg":252,"bg":240,"bold":true}],[" ",{"fg":240}],["bre                                                                                                                                                                                                            ",{}]]},"cursor":{"x":34}}],[0.08794200000000001,{"lines":{"0":[[" INSERT ",{"fg":22,"bg":148,"bold":true}],[" ",{"fg":148,"bg":31}],["wilmoore ",{"fg":231,"bg":31,"bold":true}],[" ",{"fg":31,"bg":240}],["/ ",{"fg":250,"bg":240}],[" ",{"fg":245,"bg":240}],["tmp ",{"fg":252,"bg":240,"bold":true}],[" ",{"fg":240}],["brew                                                                                                                                                                                                           ",{}]]},"cursor":{"x":35}}],[0.256068,{"cursor":{"x":36}}],[0.31152,{"lines":{"0":[[" INSERT ",{"fg":22,"bg":148,"bold":true}],[" ",{"fg":148,"bg":31}],["wilmoore ",{"fg":231,"bg":31,"bold":true}],[" ",{"fg":31,"bg":240}],["/ ",{"fg":250,"bg":240}],[" ",{"fg":245,"bg":240}],["tmp ",{"fg":252,"bg":240,"bold":true}],[" ",{"fg":240}],["brew u                                                                                                                                                                                                         ",{}]]},"cursor":{"x":37}}],[0.09585,{"lines":{"0":[[" INSERT ",{"fg":22,"bg":148,"bold":true}],[" ",{"fg":148,"bg":31}],["wilmoore ",{"fg":231,"bg":31,"bold":true}],[" ",{"fg":31,"bg":240}],["/ ",{"fg":250,"bg":240}],[" ",{"fg":245,"bg":240}],["tmp ",{"fg":252,"bg":240,"bold":true}],[" ",{"fg":240}],["brew up                                                                                                                                                                                                        ",{}]]},"cursor":{"x":38}}],[0.015869,{"lines":{"0":[[" INSERT ",{"fg":22,"bg":148,"bold":true}],[" ",{"fg":148,"bg":31}],["wilmoore ",{"fg":231,"bg":31,"bold":true}],[" ",{"fg":31,"bg":240}],["/ ",{"fg":250,"bg":240}],[" ",{"fg":245,"bg":240}],["tmp ",{"fg":252,"bg":240,"bold":true}],[" ",{"fg":240}],["brew upd                                                                                                                                                                                                       ",{}]]},"cursor":{"x":39}}],[0.08817800000000001,{"lines":{"0":[[" INSERT ",{"fg":22,"bg":148,"bold":true}],[" ",{"fg":148,"bg":31}],["wilmoore ",{"fg":231,"bg":31,"bold":true}],[" ",{"fg":31,"bg":240}],["/ ",{"fg":250,"bg":240}],[" ",{"fg":245,"bg":240}],["tmp ",{"fg":252,"bg":240,"bold":true}],[" ",{"fg":240}],["brew upda                                                                                                                                                                                                      ",{}]]},"cursor":{"x":40}}],[0.152647,{"lines":{"0":[[" INSERT ",{"fg":22,"bg":148,"bold":true}],[" ",{"fg":148,"bg":31}],["wilmoore ",{"fg":231,"bg":31,"bold":true}],[" ",{"fg":31,"bg":240}],["/ ",{"fg":250,"bg":240}],[" ",{"fg":245,"bg":240}],["tmp ",{"fg":252,"bg":240,"bold":true}],[" ",{"fg":240}],["brew updat                                                                                                                                                                                                     ",{}]]},"cursor":{"x":41}}],[0.09581000000000001,{"lines":{"0":[[" INSERT ",{"fg":22,"bg":148,"bold":true}],[" ",{"fg":148,"bg":31}],["wilmoore ",{"fg":231,"bg":31,"bold":true}],[" ",{"fg":31,"bg":240}],["/ ",{"fg":250,"bg":240}],[" ",{"fg":245,"bg":240}],["tmp ",{"fg":252,"bg":240,"bold":true}],[" ",{"fg":240}],["brew update                                                                                                                                                                                                    ",{}]]},"cursor":{"x":42}}],[1.93591,{}],[0.158542,{}],[0.000121,{"cursor":{"x":0,"y":1}}],[12.682674,{"lines":{"1":[["Already up-to-date.                                                                                                                                                                                                                           ",{}]]},"cursor":{"y":2}}],[0.002222,{}],[0.156247,{"lines":{"2":[[" INSERT ",{"fg":22,"bg":148,"bold":true}],[" ",{"fg":148,"bg":31}],["wilmoore ",{"fg":231,"bg":31,"bold":true}],[" ",{"fg":31,"bg":240}],["/ ",{"fg":250,"bg":240}],[" ",{"fg":245,"bg":240}],["tmp ",{"fg":252,"bg":240,"bold":true}],[" ",{"fg":240}],["                                                                                                                                                                                                               ",{}]]},"cursor":{"x":31}}],[0.000138,{}],[0.15849,{}],[5.435276,{"lines":{"2":[[" INSERT ",{"fg":22,"bg":148,"bold":true}],[" ",{"fg":148,"bg":31}],["wilmoore ",{"fg":231,"bg":31,"bold":true}],[" ",{"fg":31,"bg":240}],["/ ",{"fg":250,"bg":240}],[" ",{"fg":245,"bg":240}],["tmp ",{"fg":252,"bg":240,"bold":true}],[" ",{"fg":240}],["b                                                                                                                                                                                                              ",{}]]},"cursor":{"x":32}}],[0.00326,{"lines":{"2":[[" INSERT ",{"fg":22,"bg":148,"bold":true}],[" ",{"fg":148,"bg":31}],["wilmoore ",{"fg":231,"bg":31,"bold":true}],[" ",{"fg":31,"bg":240}],["/ ",{"fg":250,"bg":240}],[" ",{"fg":245,"bg":240}],["tmp ",{"fg":252,"bg":240,"bold":true}],[" ",{"fg":240}],["brew install influxdb                                                                                                                                                                                          ",{}]]},"cursor":{"x":52}}],[0.298129,{}],[0.15793,{}],[3e-05,{"cursor":{"x":0,"y":3}}],[0.592402,{"lines":{"3":[["Warning",{"fg":1,"underline":true}],[": Building source; cellar of influxdb's bottle is /usr/local/Cellar                                                                                                                                                                    ",{}]]},"cursor":{"y":4}}],[0.213032,{"lines":{"4":[["==>",{"fg":4,"bold":true}],[" Downloading http://get.influxdb.org/influxdb-0.7.1.src.tar.gz",{"bold":true}],["                                                                                                                                                                             ",{}]]},"cursor":{"y":5}}],[0.00039,{"lines":{"5":[["Already downloaded: /Library/Caches/Homebrew/influxdb-0.7.1.tar.gz                                                                                                                                                                            ",{}]]},"cursor":{"y":6}}],[0.396422,{"lines":{"6":[["==>",{"fg":4,"bold":true}],[" ./configure --with-flex=/Users/wilmoore/.homebrew/Cellar/flex/2.5.37/bin/flex --with-bison=/Users/wilmoore/.homebrew/Cellar/bison/3.0.2/bin/bison",{"bold":true}],["                                                                                         ",{}]]},"cursor":{"y":7}}],[0.505557,{"lines":{"7":[["==>",{"fg":4,"bold":true}],[" make dependencies protobuf parser",{"bold":true}],["                                                                                                                                                                                                         ",{}]]},"cursor":{"y":8}}],[1.85618,{"lines":{"8":[["==>",{"fg":4,"bold":true}],[" go build daemon",{"bold":true}],["                                                                                                                                                                                                                           ",{}]]},"cursor":{"y":9}}],[2.827384,{"lines":{"9":[["      _leveldb_property_value in libleveldb.a(c.o)                                                                                                                                                                                            ",{}]],"10":[["      _leveldb_destroy_db in libleveldb.a(c.o)                                                                                                                                                                                                ",{}]],"11":[["      ...                                                                                                                                                                                                                                     ",{}]],"12":[["ld: symbol(s) not found for architecture x86_64                                                                                                                                                                                               ",{}]],"13":[["clang: error: linker command failed with exit code 1 (use -v to see invocation)                                                                                                                                                               ",{}]]},"cursor":{"y":14}}],[0.776715,{"lines":{"15":[["READ THIS",{"fg":1,"underline":true}],[": ",{}],["https://github.com/Homebrew/homebrew/wiki/troubleshooting",{"underline":true}],["                                                                                                                                                                          ",{}]]},"cursor":{"y":17}}],[0.455632,{}],[0.164966,{"lines":{"17":[[" INSERT ",{"fg":22,"bg":148,"bold":true}],[" ",{"fg":148,"bg":31}],["wilmoore ",{"fg":231,"bg":31,"bold":true}],[" ",{"fg":31,"bg":240}],["/ ",{"fg":250,"bg":240}],[" ",{"fg":245,"bg":240}],["tmp ",{"fg":252,"bg":240,"bold":true}],[" ",{"fg":240}],["                                                                                                                                                                                                         ",{}],[" ",{"fg":52}],[" 1 ",{"fg":231,"bg":52}],[" ",{}]]},"cursor":{"x":31}}],[9.1e-05,{}],[0.153229,{"lines":{"17":[[" INSERT ",{"fg":22,"bg":148,"bold":true}],[" ",{"fg":148,"bg":31}],["wilmoore ",{"fg":231,"bg":31,"bold":true}],[" ",{"fg":31,"bg":240}],["/ ",{"fg":250,"bg":240}],[" ",{"fg":245,"bg":240}],["tmp ",{"fg":252,"bg":240,"bold":true}],[" ",{"fg":240}],["                                                                                                                                                                                                               ",{}]]}}],[2.044972,{"lines":{"17":[[" INSERT ",{"fg":22,"bg":148,"bold":true}],[" ",{"fg":148,"bg":31}],["wilmoore ",{"fg":231,"bg":31,"bold":true}],[" ",{"fg":31,"bg":240}],["/ ",{"fg":250,"bg":240}],[" ",{"fg":245,"bg":240}],["tmp ",{"fg":252,"bg":240,"bold":true}],[" ",{"fg":240}],["e                                                                                                                                                                                                              ",{}]]},"cursor":{"x":32}}],[0.152029,{"lines":{"17":[[" INSERT ",{"fg":22,"bg":148,"bold":true}],[" ",{"fg":148,"bg":31}],["wilmoore ",{"fg":231,"bg":31,"bold":true}],[" ",{"fg":31,"bg":240}],["/ ",{"fg":250,"bg":240}],[" ",{"fg":245,"bg":240}],["tmp ",{"fg":252,"bg":240,"bold":true}],[" ",{"fg":240}],["ex                                                                                                                                                                                                             ",{}]]},"cursor":{"x":33}}],[0.112095,{"lines":{"17":[[" INSERT ",{"fg":22,"bg":148,"bold":true}],[" ",{"fg":148,"bg":31}],["wilmoore ",{"fg":231,"bg":31,"bold":true}],[" ",{"fg":31,"bg":240}],["/ ",{"fg":250,"bg":240}],[" ",{"fg":245,"bg":240}],["tmp ",{"fg":252,"bg":240,"bold":true}],[" ",{"fg":240}],["exi                                                                                                                                                                                                            ",{}]]},"cursor":{"x":34}}],[0.143874,{"lines":{"17":[[" INSERT ",{"fg":22,"bg":148,"bold":true}],[" ",{"fg":148,"bg":31}],["wilmoore ",{"fg":231,"bg":31,"bold":true}],[" ",{"fg":31,"bg":240}],["/ ",{"fg":250,"bg":240}],[" ",{"fg":245,"bg":240}],["tmp ",{"fg":252,"bg":240,"bold":true}],[" ",{"fg":240}],["exit                                                                                                                                                                                                           ",{}]]},"cursor":{"x":35}}],[0.167646,{}],[0.155159,{}],[7.499999999999999e-05,{"cursor":{"x":0,"y":18}}]]